ilqrext.cpython-36m-x86_64-linux-gnu.so
sqpext.cpython-36m-x86_64-linux-gnu.so
horizon/__init__.py
horizon/functions.py
horizon/misc_function.py
horizon/problem.py
horizon/type_doc.py
horizon/variables.py
horizon/cpp/CMakeLists.txt
horizon/cpp/CMakeLists.txt.orig
horizon/cpp/pyilqr.cpp
horizon/cpp/pyilqr_helpers.h
horizon/cpp/pysqp.cpp
horizon/cpp/pysqp_helpers.h
horizon/cpp/src/codegen_function.cpp
horizon/cpp/src/codegen_function.h
horizon/cpp/src/horizon_parser.cpp
horizon/cpp/src/horizon_parser.h
horizon/cpp/src/ilqr.cpp
horizon/cpp/src/ilqr.h
horizon/cpp/src/ilqr_backward_pass.cpp
horizon/cpp/src/ilqr_forward_pass.cpp
horizon/cpp/src/ilqr_impl.h
horizon/cpp/src/ilqr_test.cpp
horizon/cpp/src/iterate_filter.cpp
horizon/cpp/src/iterate_filter.h
horizon/cpp/src/profiling.cpp
horizon/cpp/src/profiling.h
horizon/cpp/src/sqp.h
horizon/cpp/src/sqp_test.cpp
horizon/cpp/src/wrapped_function.cpp
horizon/cpp/src/wrapped_function.h
horizon/cpp/tests/CMakeLists.txt
horizon/cpp/tests/testCasadiUtils.cpp
horizon/cpp/tests/testQr.cpp
horizon/examples/__init__.py
horizon/examples/cart_pole.py
horizon/examples/package.xml
horizon/examples/quadruped.py
horizon/examples/roped_robot.py
horizon/examples/roped_robot_rappel.py
horizon/examples/roped_robot_sim.py
horizon/examples/spot.py
horizon/examples/spot_motions.py
horizon/examples/spot_walk.py
horizon/examples/unit_mass.py
horizon/examples/replay/launch/launcher.launch
horizon/examples/replay/rviz/cart_pole.rviz
horizon/examples/replay/rviz/cart_pole_xy.rviz
horizon/examples/replay/rviz/quadruped_template.rviz
horizon/examples/replay/rviz/roped_template.rviz
horizon/examples/replay/rviz/spot.rviz
horizon/examples/urdf/cart_pole.urdf
horizon/examples/urdf/cart_pole_xy.urdf
horizon/examples/urdf/lwr.urdf
horizon/examples/urdf/quadruped_template.urdf
horizon/examples/urdf/roped_template.urdf
horizon/examples/urdf/spot.urdf
horizon/external_libs/libcasadi.so.3.6
horizon/external_libs/libcasadi_conic_osqp.so
casadi_horizon-0.4.5.dist-info/LICENSE.txt
casadi_horizon-0.4.5.dist-info/METADATA
casadi_horizon-0.4.5.dist-info/WHEEL
casadi_horizon-0.4.5.dist-info/top_level.txt
casadi_horizon-0.4.5.dist-info/RECORD
