Metadata-Version: 2.1
Name: casadi-horizon
Version: 0.4.5
Summary: Library for Trajectory Optimization based on CasADi
Home-page: https://github.com/ADVRHumanoids/horizon
Author: Francesco Ruscelli
Author-email: francesco.ruscelli@iit.it
License: UNKNOWN
Platform: UNKNOWN
Requires-Python: >=3.6
License-File: LICENSE.txt
Requires-Dist: casadi
Requires-Dist: numpy
Requires-Dist: matplotlib
Requires-Dist: scipy
Requires-Dist: casadi-kin-dyn
Requires-Dist: rospkg
